ot_logging_helpers/__init__.py
ot_logging_helpers/configuration.py
ot_logging_helpers/custom_formatter.py
ot_logging_helpers/log_context.py
ot_logging_helpers-0.1.1.dist-info/METADATA
ot_logging_helpers-0.1.1.dist-info/WHEEL
ot_logging_helpers-0.1.1.dist-info/top_level.txt
ot_logging_helpers-0.1.1.dist-info/RECORD
