Metadata-Version: 2.1
Name: ot_logging_helpers
Version: 0.1.1
Summary: Python Logging Helpers
Home-page: https://github.com/orthanc-team/ot-logging-helpers
Author: Orthanc Team
Author-email: info@orthanc.team
Project-URL: Bug Reports, https://github.com/orthanc-team/ot-logging-helpers/issues
Project-URL: Funding, https://orthanc-team
Project-URL: Source, https://github.com/orthanc-team/ot-logging-helpers/
Keywords: logging
Classifier: Development Status :: 3 - Alpha
Classifier: Intended Audience :: Developers
Classifier: License :: OSI Approved :: GNU Lesser General Public License v3 (LGPLv3)
Classifier: Programming Language :: Python :: 3
Classifier: Programming Language :: Python :: 3.8
Classifier: Programming Language :: Python :: 3.9
Classifier: Programming Language :: Python :: 3.10
Classifier: Programming Language :: Python :: 3.11
Classifier: Programming Language :: Python :: 3.12
Classifier: Programming Language :: Python :: 3 :: Only
Requires-Python: >=3.8, <4
Provides-Extra: dev
Requires-Dist: check-manifest ; extra == 'dev'
Requires-Dist: pytest ; extra == 'dev'
Provides-Extra: test
Requires-Dist: coverage ; extra == 'test'
Requires-Dist: pytest ; extra == 'test'
